Metadata-Version: 1.1
Name: modmagic
Version: 0.0.1
Summary: IPython mod(ule) magic
Home-page: https://github.com/yungyuc/modmagic
Author: Yung-Yu Chen
Author-email: yyc@solvcon.net
License: BSD
Platform: UNKNOWN
Classifier: Programming Language :: Python
Classifier: Intended Audience :: Developers
Classifier: License :: OSI Approved :: BSD License
Classifier: Framework :: IPython
Classifier: Topic :: Software Development :: Libraries
Classifier: Topic :: Utilities
